{"page":41,"statuses":[
{"avatar":"http://tp2.sinaimg.cn/1912962585/50/1299375629/0","created_at":"Tue Jun 12 20:29:15 +0800 2012","type":"else","name":"当归中医学堂","author":"idanggui","id":"3456186152460396","text":"｛迅速缓解偏头痛｝偏头痛疼起来很要命，中医有一种止痛迅速，而无副作用的方法：川芎20克，白芷20克，远志20克，冰片2，共研细末，密封，用纱布包少许药粉塞鼻孔，右侧头疼塞左侧，左侧疼塞右侧。鼻粘膜对药物吸收很迅速，药力“纳鼻而传十二经”， 塞30分钟即可。注意：一定要塞对侧鼻孔。#当归生活#"},
{"avatar":"http://tp4.sinaimg.cn/1974766635/50/5621938128/1","created_at":"Tue Jun 12 20:29:47 +0800 2012","type":"else","name":"中医养生资讯","author":"123071200","id":"3456186118897886","text":"【鱼针灸后更鲜美】日本大阪的一家公司日前在日本国际海产品展示会上展示了给金枪鱼做针灸的技术并已申请了专利。该公司表示针灸能让金枪鱼平静下来，在忍受死亡痛苦时翻滚得没有以前剧烈。金枪鱼针灸后，其血液会更纯净,肉质会更鲜美。针灸后的金枪鱼无需喂食药物，经过运输后肉质也能保持新鲜。"},
{"avatar":"http://tp3.sinaimg.cn/1919233922/50/5600497604/0","created_at":"Tue Jun 12 20:30:31 +0800 2012","type":"else","name":"健康瘦身宝典","author":"beslim","id":"3456185896198008","text":"【瘦腰——经典仰起】最有效的仰起动作，特别抢救腹部。1、仰面平躺，双手放在耳后，屈双膝，双脚分开同肩宽。2、呼气，向上抬起身体，到眼睛可以平视膝盖即可，吸气停留数秒。呼气平躺。重复动作8-10次。"},
{"avatar":"http://tp1.sinaimg.cn/2313553984/50/5614664250/1","created_at":"Tue Jun 12 23:44:19 +0800 2012","type":"else","name":"健康小秘方","author":"u/2313553984","id":"3456240561148286","text":"【女性常吃鱼有助预防乳腺肿瘤】研究发现，与很少吃鱼的 女性比，每天吃鱼的女性，患乳腺肿瘤几率会降43%。鱼肉富含欧米伽3脂肪酸，能抑制肿瘤细胞增长，预防乳腺肿瘤。优选金枪鱼、沙丁鱼、三文鱼等深海鱼，其欧米伽3脂肪酸含量高。"},
{"avatar":"http://tp1.sinaimg.cn/2167401224/50/5622079846/1","created_at":"Tue Jun 12 23:44:29 +0800 2012","type":"else","name":"运动健身吧","author":"u/2167401224","id":"3456240548562506","text":"【日常保健6招】1.中午小睡，让身体得到缓冲； 2.不滥用抗生素，让免疫力适当练兵； 3.乐享工作不过劳，合理作息； 4.常用温水沐脚，并按摩脚部； 5.增加户外运动，享受阳光；6.面对朋友、同事、困难，保持微笑。"},
{"avatar":"http://tp2.sinaimg.cn/2141299913/50/5633240772/0","created_at":"Tue Jun 12 23:45:16 +0800 2012","type":"else","name":"热门新视觉","author":"xsdqm","id":"3456153021489988","text":"【一辈子至少要去一次的八个中国小镇】1、最美的地方——乌镇。2、人间天堂——丽江古城。3、现代桃花源——水墨婺源。4、风雨边城——凤凰古城。5、人间天上——九寨沟。6、最完整的古县城——平遥。7、艺术之都——敦煌。8、西部第一村——新疆布尔津白哈巴村。[给劲] @热门新视觉"},
{"avatar":"http://tp2.sinaimg.cn/2709880513/50/5629699534/1","created_at":"Tue Jun 12 23:45:34 +0800 2012","type":"else","name":"绿美人生","author":"lvmeelife","id":"3455079417980897","text":"【老年健康饮食10项注意】①质量宜高：豆蛋奶，多鱼少肉②食物宜杂，注意搭配；③蔬果宜鲜；④数量宜少，每餐七八分饱；⑤质地宜软，易于消化；⑥饭菜宜香，增加食欲；⑦饮水宜多，喝淡茶或白开水；⑧温度宜热，利于肠道消化；⑨饮食宜淡，口味忌重；⑩速度宜缓，细嚼慢咽。"},
{"avatar":"http://tp3.sinaimg.cn/1689974542/50/5622877001/1","created_at":"Tue Jun 12 23:46:05 +0800 2012","type":"else","name":"健康顾问微博","author":"alb6655","id":"3456238568738895","text":"【智商高的人睡眠少】智商高的人，往往拥有较多的兴奋性神经物质，思维活跃，灵感随时涌现，兴奋状态时间长，需要的睡眠时间就比较短。据称，大部分成年人需要的睡眠时间是7-8小时，不建议超过9小时。据说智商160以上的爱因斯坦每天只睡1到3个小时。"},
{"avatar":"http://tp2.sinaimg.cn/2808092557/50/5634478745/0","created_at":"Tue Jun 12 23:46:28 +0800 2012","type":"else","name":"时尚健康顾问","author":"u/2808092557","id":"3456232537073481","text":"复旦大学教师于娟乳腺癌辞世。生前日记：“在生死临界点的时候，你会发现，任何的加班（长期熬夜等于慢性自杀），给自己太多的压力，买房买车的需求，这些都是浮云。如果有时间，好好陪陪你的孩子，把买车的钱给父母亲买双鞋子，不要拼命去换什么大房子，和相爱的人在一起，蜗居也温暖。”"},
{"avatar":"http://tp4.sinaimg.cn/2673164251/50/5627178578/0","created_at":"Tue Jun 12 23:46:57 +0800 2012","type":"else","name":"姐的世界有你","author":"u/2673164251","id":"3456237272798673","text":"【研究表明：女人多吃鸡蛋或致死亡 】 据 学者进行的一项长达14年的研究，每天吃一个或以上数量鸡蛋的妇女，与每周只吃一个或两个鸡蛋的妇女相比，死亡率要高一些.....。 http://t.cn/zO0BAE8"},
{"avatar":"http://tp2.sinaimg.cn/1982718541/50/1298876301/1","created_at":"Tue Jun 12 23:48:00 +0800 2012","type":"else","name":"养生坛","author":"yangshengtan","id":"3456058221340917","text":"【20妙招教你如何防蚊止痒】①多吃碱性蔬菜。②把蒜瓣切开，用断面涂抹蚊子咬的包止痒。③用八角、茴各两枚，泡于温水中用其水洗澡，蚊子不敢近身。④维生素B1泡水擦身也会让蚊子不敢近身。⑤在室内点燃干桔皮，能驱蚊又可消除屋内异味。⑥穿浅色衣服。更多请进：http://t.cn/zWvQhhr (康康)"},
{"avatar":"http://tp2.sinaimg.cn/1652194081/50/5633530295/0","created_at":"Tue Jun 12 23:48:43 +0800 2012","type":"else","name":"美容健康","author":"jipinmeinv","id":"3456236722975033","text":"【驱蚊小智慧】：1.用橘红色玻璃纸或绸布套在灯泡上,蚊子最怕橘红色光；2.在身上或枕头上洒些香水；3.将樟脑丸磨碎撒在屋内墙角；4.在室内的花盆里栽一两株西红柿,西红柿枝叶的气味会把蚊子赶走；5.在灯下挂一把香葱,或用纱袋装几根葱段,各种小虫都不会飞来；6.在房间放几盒开盖的风油精清凉油。"},
{"avatar":"http://tp2.sinaimg.cn/2174942061/50/5622714476/0","created_at":"Tue Jun 12 23:50:22 +0800 2012","type":"else","name":"养生健康一身轻","author":"u/2174942061","id":"3456048578711069","text":"【脊椎有问题的7个信号】①鞋后跟常被磨得高低不平；②头部总不自觉地偏向一侧，一条腿总想搭到另一条腿上，不留神时走路时身体总向一侧倾斜；③不能十分舒适地进行深呼吸；④下颌时常发出“咔哒”声；⑤颈部、背部发出哗哗声；⑥精神不能很好地集中；⑦常闪腰、岔气。为每一个你关心的人而转！"},
{"avatar":"http://tp2.sinaimg.cn/2709880513/50/5629699534/1","created_at":"Tue Jun 12 23:52:06 +0800 2012","type":"else","name":"绿美人生","author":"lvmeelife","id":"3456220944079337","text":"【美白抗衰老水果】1.苹果：保湿、抑制黑色素沉着、淡化雀斑黄褐斑，抗癌防衰老；2.猕猴桃：增白、消除雀斑和暗疮、增强皮肤的抗衰老能力；3.草莓增白和滋润保湿；4.樱桃能促进角质层的形成；5.桃子防止色素沉着，预防皱纹；6.桔子能增强肌肤弹性；7.柠檬：增白洁肤、去除色斑、紧肤、润肤、抗老化等。"},
{"avatar":"http://tp1.sinaimg.cn/2167401224/50/5622079846/1","created_at":"Wed Jun 13 00:08:01 +0800 2012","type":"else","name":"运动健身吧","author":"u/2167401224","id":"3456248098160286","text":"【健康小知识】1、空腹时不要吃蕃茄, 最好饭后吃 2、早上醒来.先喝一杯水. 预防结石 3、睡前三小时不要吃东西. 会胖 4、少喝奶茶. 因为高热量.高油.没有营养价值可言.长期饮用.易罹患高血压.糖尿病.等疾病 5、刚出炉的面包 不宜马上食用 6、远离充电座. 人体应远离30公分以上.切忌放在床边。"}
]}